{
    "numCats": [
        7, 
        4, 
        3, 
        4
    ], 
    "varCats": [
        {
            "cats": [
                "NHWhite", 
                " Black", 
                " Asian", 
                " Hispanic", 
                " AmIndian", 
                " NHOther", 
                " NHMulti"
            ], 
            "name": "RaceEth"
        }, 
        {
            "cats": [
                "LTHS", 
                "HsGrad", 
                "SomeColl", 
                "CollGrad"
            ], 
            "name": "Educ"
        }, 
        {
            "cats": [
                "None", 
                "Kids<6", 
                "KidsOther"
            ], 
            "name": "Kids"
        }, 
        {
            "cats": [
                "EmpFull", 
                "EmpPart", 
                "Unempd", 
                "NILF"
            ], 
            "name": "Emp2"
        }
    ], 
    "title": "2008 Employment status by number of children, education for currently married women, age 25-34, wgtd 2006-08 ACS, SSDAN/U-Mich", 
    "numOfVars": 4, 
    "varNames": [
        "RaceEth", 
        "Educ", 
        "Kids", 
        "Emp2"
    ], 
    "theData": [
        {
            "Dep": "17542", 
            "RaceEth": "NHWhite", 
            "Kids": "None", 
            "Emp2": "EmpFull", 
            "Educ": "LTHS"
        }, 
        {
            "Dep": "5009", 
            "RaceEth": "NHWhite", 
            "Kids": "None", 
            "Emp2": "EmpPart", 
            "Educ": "LTHS"
        }, 
        {
            "Dep": "5129", 
            "RaceEth": "NHWhite", 
            "Kids": "None", 
            "Emp2": "Unempd", 
            "Educ": "LTHS"
        }, 
        {
            "Dep": "20683", 
            "RaceEth": "NHWhite", 
            "Kids": "None", 
            "Emp2": "NILF", 
            "Educ": "LTHS"
        }, 
        {
            "Dep": "36595", 
            "RaceEth": "NHWhite", 
            "Kids": "Kids<6", 
            "Emp2": "EmpFull", 
            "Educ": "LTHS"
        }, 
        {
            "Dep": "27752", 
            "RaceEth": "NHWhite", 
            "Kids": "Kids<6", 
            "Emp2": "EmpPart", 
            "Educ": "LTHS"
        }, 
        {
            "Dep": "9780", 
            "RaceEth": "NHWhite", 
            "Kids": "Kids<6", 
            "Emp2": "Unempd", 
            "Educ": "LTHS"
        }, 
        {
            "Dep": "106310", 
            "RaceEth": "NHWhite", 
            "Kids": "Kids<6", 
            "Emp2": "NILF", 
            "Educ": "LTHS"
        }, 
        {
            "Dep": "27884", 
            "RaceEth": "NHWhite", 
            "Kids": "KidsOther", 
            "Emp2": "EmpFull", 
            "Educ": "LTHS"
        }, 
        {
            "Dep": "14567", 
            "RaceEth": "NHWhite", 
            "Kids": "KidsOther", 
            "Emp2": "EmpPart", 
            "Educ": "LTHS"
        }, 
        {
            "Dep": "7303", 
            "RaceEth": "NHWhite", 
            "Kids": "KidsOther", 
            "Emp2": "Unempd", 
            "Educ": "LTHS"
        }, 
        {
            "Dep": "42596", 
            "RaceEth": "NHWhite", 
            "Kids": "KidsOther", 
            "Emp2": "NILF", 
            "Educ": "LTHS"
        }, 
        {
            "Dep": "154211", 
            "RaceEth": "NHWhite", 
            "Kids": "None", 
            "Emp2": "EmpFull", 
            "Educ": "HsGrad"
        }, 
        {
            "Dep": "34738", 
            "RaceEth": "NHWhite", 
            "Kids": "None", 
            "Emp2": "EmpPart", 
            "Educ": "HsGrad"
        }, 
        {
            "Dep": "11237", 
            "RaceEth": "NHWhite", 
            "Kids": "None", 
            "Emp2": "Unempd", 
            "Educ": "HsGrad"
        }, 
        {
            "Dep": "53989", 
            "RaceEth": "NHWhite", 
            "Kids": "None", 
            "Emp2": "NILF", 
            "Educ": "HsGrad"
        }, 
        {
            "Dep": "273408", 
            "RaceEth": "NHWhite", 
            "Kids": "Kids<6", 
            "Emp2": "EmpFull", 
            "Educ": "HsGrad"
        }, 
        {
            "Dep": "144429", 
            "RaceEth": "NHWhite", 
            "Kids": "Kids<6", 
            "Emp2": "EmpPart", 
            "Educ": "HsGrad"
        }, 
        {
            "Dep": "29286", 
            "RaceEth": "NHWhite", 
            "Kids": "Kids<6", 
            "Emp2": "Unempd", 
            "Educ": "HsGrad"
        }, 
        {
            "Dep": "331749", 
            "RaceEth": "NHWhite", 
            "Kids": "Kids<6", 
            "Emp2": "NILF", 
            "Educ": "HsGrad"
        }, 
        {
            "Dep": "173197", 
            "RaceEth": "NHWhite", 
            "Kids": "KidsOther", 
            "Emp2": "EmpFull", 
            "Educ": "HsGrad"
        }, 
        {
            "Dep": "67236", 
            "RaceEth": "NHWhite", 
            "Kids": "KidsOther", 
            "Emp2": "EmpPart", 
            "Educ": "HsGrad"
        }, 
        {
            "Dep": "15992", 
            "RaceEth": "NHWhite", 
            "Kids": "KidsOther", 
            "Emp2": "Unempd", 
            "Educ": "HsGrad"
        }, 
        {
            "Dep": "87875", 
            "RaceEth": "NHWhite", 
            "Kids": "KidsOther", 
            "Emp2": "NILF", 
            "Educ": "HsGrad"
        }, 
        {
            "Dep": "340551", 
            "RaceEth": "NHWhite", 
            "Kids": "None", 
            "Emp2": "EmpFull", 
            "Educ": "SomeColl"
        }, 
        {
            "Dep": "72522", 
            "RaceEth": "NHWhite", 
            "Kids": "None", 
            "Emp2": "EmpPart", 
            "Educ": "SomeColl"
        }, 
        {
            "Dep": "15430", 
            "RaceEth": "NHWhite", 
            "Kids": "None", 
            "Emp2": "Unempd", 
            "Educ": "SomeColl"
        }, 
        {
            "Dep": "63500", 
            "RaceEth": "NHWhite", 
            "Kids": "None", 
            "Emp2": "NILF", 
            "Educ": "SomeColl"
        }, 
        {
            "Dep": "555141", 
            "RaceEth": "NHWhite", 
            "Kids": "Kids<6", 
            "Emp2": "EmpFull", 
            "Educ": "SomeColl"
        }, 
        {
            "Dep": "296522", 
            "RaceEth": "NHWhite", 
            "Kids": "Kids<6", 
            "Emp2": "EmpPart", 
            "Educ": "SomeColl"
        }, 
        {
            "Dep": "36935", 
            "RaceEth": "NHWhite", 
            "Kids": "Kids<6", 
            "Emp2": "Unempd", 
            "Educ": "SomeColl"
        }, 
        {
            "Dep": "478827", 
            "RaceEth": "NHWhite", 
            "Kids": "Kids<6", 
            "Emp2": "NILF", 
            "Educ": "SomeColl"
        }, 
        {
            "Dep": "222175", 
            "RaceEth": "NHWhite", 
            "Kids": "KidsOther", 
            "Emp2": "EmpFull", 
            "Educ": "SomeColl"
        }, 
        {
            "Dep": "78231", 
            "RaceEth": "NHWhite", 
            "Kids": "KidsOther", 
            "Emp2": "EmpPart", 
            "Educ": "SomeColl"
        }, 
        {
            "Dep": "13305", 
            "RaceEth": "NHWhite", 
            "Kids": "KidsOther", 
            "Emp2": "Unempd", 
            "Educ": "SomeColl"
        }, 
        {
            "Dep": "79767", 
            "RaceEth": "NHWhite", 
            "Kids": "KidsOther", 
            "Emp2": "NILF", 
            "Educ": "SomeColl"
        }, 
        {
            "Dep": "851825", 
            "RaceEth": "NHWhite", 
            "Kids": "None", 
            "Emp2": "EmpFull", 
            "Educ": "CollGrad"
        }, 
        {
            "Dep": "92058", 
            "RaceEth": "NHWhite", 
            "Kids": "None", 
            "Emp2": "EmpPart", 
            "Educ": "CollGrad"
        }, 
        {
            "Dep": "20356", 
            "RaceEth": "NHWhite", 
            "Kids": "None", 
            "Emp2": "Unempd", 
            "Educ": "CollGrad"
        }, 
        {
            "Dep": "76957", 
            "RaceEth": "NHWhite", 
            "Kids": "None", 
            "Emp2": "NILF", 
            "Educ": "CollGrad"
        }, 
        {
            "Dep": "735264", 
            "RaceEth": "NHWhite", 
            "Kids": "Kids<6", 
            "Emp2": "EmpFull", 
            "Educ": "CollGrad"
        }, 
        {
            "Dep": "300598", 
            "RaceEth": "NHWhite", 
            "Kids": "Kids<6", 
            "Emp2": "EmpPart", 
            "Educ": "CollGrad"
        }, 
        {
            "Dep": "19369", 
            "RaceEth": "NHWhite", 
            "Kids": "Kids<6", 
            "Emp2": "Unempd", 
            "Educ": "CollGrad"
        }, 
        {
            "Dep": "424700", 
            "RaceEth": "NHWhite", 
            "Kids": "Kids<6", 
            "Emp2": "NILF", 
            "Educ": "CollGrad"
        }, 
        {
            "Dep": "89996", 
            "RaceEth": "NHWhite", 
            "Kids": "KidsOther", 
            "Emp2": "EmpFull", 
            "Educ": "CollGrad"
        }, 
        {
            "Dep": "17558", 
            "RaceEth": "NHWhite", 
            "Kids": "KidsOther", 
            "Emp2": "EmpPart", 
            "Educ": "CollGrad"
        }, 
        {
            "Dep": "2363", 
            "RaceEth": "NHWhite", 
            "Kids": "KidsOther", 
            "Emp2": "Unempd", 
            "Educ": "CollGrad"
        }, 
        {
            "Dep": "16157", 
            "RaceEth": "NHWhite", 
            "Kids": "KidsOther", 
            "Emp2": "NILF", 
            "Educ": "CollGrad"
        }, 
        {
            "Dep": "5598", 
            "RaceEth": " Black", 
            "Kids": "None", 
            "Emp2": "EmpFull", 
            "Educ": "LTHS"
        }, 
        {
            "Dep": "1749", 
            "RaceEth": " Black", 
            "Kids": "None", 
            "Emp2": "EmpPart", 
            "Educ": "LTHS"
        }, 
        {
            "Dep": "1399", 
            "RaceEth": " Black", 
            "Kids": "None", 
            "Emp2": "Unempd", 
            "Educ": "LTHS"
        }, 
        {
            "Dep": "5691", 
            "RaceEth": " Black", 
            "Kids": "None", 
            "Emp2": "NILF", 
            "Educ": "LTHS"
        }, 
        {
            "Dep": "8602", 
            "RaceEth": " Black", 
            "Kids": "Kids<6", 
            "Emp2": "EmpFull", 
            "Educ": "LTHS"
        }, 
        {
            "Dep": "2871", 
            "RaceEth": " Black", 
            "Kids": "Kids<6", 
            "Emp2": "EmpPart", 
            "Educ": "LTHS"
        }, 
        {
            "Dep": "3614", 
            "RaceEth": " Black", 
            "Kids": "Kids<6", 
            "Emp2": "Unempd", 
            "Educ": "LTHS"
        }, 
        {
            "Dep": "13582", 
            "RaceEth": " Black", 
            "Kids": "Kids<6", 
            "Emp2": "NILF", 
            "Educ": "LTHS"
        }, 
        {
            "Dep": "6244", 
            "RaceEth": " Black", 
            "Kids": "KidsOther", 
            "Emp2": "EmpFull", 
            "Educ": "LTHS"
        }, 
        {
            "Dep": "2523", 
            "RaceEth": " Black", 
            "Kids": "KidsOther", 
            "Emp2": "EmpPart", 
            "Educ": "LTHS"
        }, 
        {
            "Dep": "2177", 
            "RaceEth": " Black", 
            "Kids": "KidsOther", 
            "Emp2": "Unempd", 
            "Educ": "LTHS"
        }, 
        {
            "Dep": "4631", 
            "RaceEth": " Black", 
            "Kids": "KidsOther", 
            "Emp2": "NILF", 
            "Educ": "LTHS"
        }, 
        {
            "Dep": "24276", 
            "RaceEth": " Black", 
            "Kids": "None", 
            "Emp2": "EmpFull", 
            "Educ": "HsGrad"
        }, 
        {
            "Dep": "4300", 
            "RaceEth": " Black", 
            "Kids": "None", 
            "Emp2": "EmpPart", 
            "Educ": "HsGrad"
        }, 
        {
            "Dep": "3752", 
            "RaceEth": " Black", 
            "Kids": "None", 
            "Emp2": "Unempd", 
            "Educ": "HsGrad"
        }, 
        {
            "Dep": "11372", 
            "RaceEth": " Black", 
            "Kids": "None", 
            "Emp2": "NILF", 
            "Educ": "HsGrad"
        }, 
        {
            "Dep": "45025", 
            "RaceEth": " Black", 
            "Kids": "Kids<6", 
            "Emp2": "EmpFull", 
            "Educ": "HsGrad"
        }, 
        {
            "Dep": "12228", 
            "RaceEth": " Black", 
            "Kids": "Kids<6", 
            "Emp2": "EmpPart", 
            "Educ": "HsGrad"
        }, 
        {
            "Dep": "6843", 
            "RaceEth": " Black", 
            "Kids": "Kids<6", 
            "Emp2": "Unempd", 
            "Educ": "HsGrad"
        }, 
        {
            "Dep": "24817", 
            "RaceEth": " Black", 
            "Kids": "Kids<6", 
            "Emp2": "NILF", 
            "Educ": "HsGrad"
        }, 
        {
            "Dep": "31274", 
            "RaceEth": " Black", 
            "Kids": "KidsOther", 
            "Emp2": "EmpFull", 
            "Educ": "HsGrad"
        }, 
        {
            "Dep": "4059", 
            "RaceEth": " Black", 
            "Kids": "KidsOther", 
            "Emp2": "EmpPart", 
            "Educ": "HsGrad"
        }, 
        {
            "Dep": "4016", 
            "RaceEth": " Black", 
            "Kids": "KidsOther", 
            "Emp2": "Unempd", 
            "Educ": "HsGrad"
        }, 
        {
            "Dep": "8529", 
            "RaceEth": " Black", 
            "Kids": "KidsOther", 
            "Emp2": "NILF", 
            "Educ": "HsGrad"
        }, 
        {
            "Dep": "37670", 
            "RaceEth": " Black", 
            "Kids": "None", 
            "Emp2": "EmpFull", 
            "Educ": "SomeColl"
        }, 
        {
            "Dep": "7038", 
            "RaceEth": " Black", 
            "Kids": "None", 
            "Emp2": "EmpPart", 
            "Educ": "SomeColl"
        }, 
        {
            "Dep": "4238", 
            "RaceEth": " Black", 
            "Kids": "None", 
            "Emp2": "Unempd", 
            "Educ": "SomeColl"
        }, 
        {
            "Dep": "9717", 
            "RaceEth": " Black", 
            "Kids": "None", 
            "Emp2": "NILF", 
            "Educ": "SomeColl"
        }, 
        {
            "Dep": "90865", 
            "RaceEth": " Black", 
            "Kids": "Kids<6", 
            "Emp2": "EmpFull", 
            "Educ": "SomeColl"
        }, 
        {
            "Dep": "17608", 
            "RaceEth": " Black", 
            "Kids": "Kids<6", 
            "Emp2": "EmpPart", 
            "Educ": "SomeColl"
        }, 
        {
            "Dep": "9284", 
            "RaceEth": " Black", 
            "Kids": "Kids<6", 
            "Emp2": "Unempd", 
            "Educ": "SomeColl"
        }, 
        {
            "Dep": "32397", 
            "RaceEth": " Black", 
            "Kids": "Kids<6", 
            "Emp2": "NILF", 
            "Educ": "SomeColl"
        }, 
        {
            "Dep": "44620", 
            "RaceEth": " Black", 
            "Kids": "KidsOther", 
            "Emp2": "EmpFull", 
            "Educ": "SomeColl"
        }, 
        {
            "Dep": "7495", 
            "RaceEth": " Black", 
            "Kids": "KidsOther", 
            "Emp2": "EmpPart", 
            "Educ": "SomeColl"
        }, 
        {
            "Dep": "4053", 
            "RaceEth": " Black", 
            "Kids": "KidsOther", 
            "Emp2": "Unempd", 
            "Educ": "SomeColl"
        }, 
        {
            "Dep": "8843", 
            "RaceEth": " Black", 
            "Kids": "KidsOther", 
            "Emp2": "NILF", 
            "Educ": "SomeColl"
        }, 
        {
            "Dep": "47448", 
            "RaceEth": " Black", 
            "Kids": "None", 
            "Emp2": "EmpFull", 
            "Educ": "CollGrad"
        }, 
        {
            "Dep": "4053", 
            "RaceEth": " Black", 
            "Kids": "None", 
            "Emp2": "EmpPart", 
            "Educ": "CollGrad"
        }, 
        {
            "Dep": "2271", 
            "RaceEth": " Black", 
            "Kids": "None", 
            "Emp2": "Unempd", 
            "Educ": "CollGrad"
        }, 
        {
            "Dep": "6261", 
            "RaceEth": " Black", 
            "Kids": "None", 
            "Emp2": "NILF", 
            "Educ": "CollGrad"
        }, 
        {
            "Dep": "76041", 
            "RaceEth": " Black", 
            "Kids": "Kids<6", 
            "Emp2": "EmpFull", 
            "Educ": "CollGrad"
        }, 
        {
            "Dep": "9156", 
            "RaceEth": " Black", 
            "Kids": "Kids<6", 
            "Emp2": "EmpPart", 
            "Educ": "CollGrad"
        }, 
        {
            "Dep": "3791", 
            "RaceEth": " Black", 
            "Kids": "Kids<6", 
            "Emp2": "Unempd", 
            "Educ": "CollGrad"
        }, 
        {
            "Dep": "13883", 
            "RaceEth": " Black", 
            "Kids": "Kids<6", 
            "Emp2": "NILF", 
            "Educ": "CollGrad"
        }, 
        {
            "Dep": "17402", 
            "RaceEth": " Black", 
            "Kids": "KidsOther", 
            "Emp2": "EmpFull", 
            "Educ": "CollGrad"
        }, 
        {
            "Dep": "1403", 
            "RaceEth": " Black", 
            "Kids": "KidsOther", 
            "Emp2": "EmpPart", 
            "Educ": "CollGrad"
        }, 
        {
            "Dep": "485", 
            "RaceEth": " Black", 
            "Kids": "KidsOther", 
            "Emp2": "Unempd", 
            "Educ": "CollGrad"
        }, 
        {
            "Dep": "1603", 
            "RaceEth": " Black", 
            "Kids": "KidsOther", 
            "Emp2": "NILF", 
            "Educ": "CollGrad"
        }, 
        {
            "Dep": "5610", 
            "RaceEth": " Asian", 
            "Kids": "None", 
            "Emp2": "EmpFull", 
            "Educ": "LTHS"
        }, 
        {
            "Dep": "981", 
            "RaceEth": " Asian", 
            "Kids": "None", 
            "Emp2": "EmpPart", 
            "Educ": "LTHS"
        }, 
        {
            "Dep": "638", 
            "RaceEth": " Asian", 
            "Kids": "None", 
            "Emp2": "Unempd", 
            "Educ": "LTHS"
        }, 
        {
            "Dep": "4930", 
            "RaceEth": " Asian", 
            "Kids": "None", 
            "Emp2": "NILF", 
            "Educ": "LTHS"
        }, 
        {
            "Dep": "7740", 
            "RaceEth": " Asian", 
            "Kids": "Kids<6", 
            "Emp2": "EmpFull", 
            "Educ": "LTHS"
        }, 
        {
            "Dep": "2392", 
            "RaceEth": " Asian", 
            "Kids": "Kids<6", 
            "Emp2": "EmpPart", 
            "Educ": "LTHS"
        }, 
        {
            "Dep": "434", 
            "RaceEth": " Asian", 
            "Kids": "Kids<6", 
            "Emp2": "Unempd", 
            "Educ": "LTHS"
        }, 
        {
            "Dep": "13248", 
            "RaceEth": " Asian", 
            "Kids": "Kids<6", 
            "Emp2": "NILF", 
            "Educ": "LTHS"
        }, 
        {
            "Dep": "4167", 
            "RaceEth": " Asian", 
            "Kids": "KidsOther", 
            "Emp2": "EmpFull", 
            "Educ": "LTHS"
        }, 
        {
            "Dep": "1080", 
            "RaceEth": " Asian", 
            "Kids": "KidsOther", 
            "Emp2": "EmpPart", 
            "Educ": "LTHS"
        }, 
        {
            "Dep": "430", 
            "RaceEth": " Asian", 
            "Kids": "KidsOther", 
            "Emp2": "Unempd", 
            "Educ": "LTHS"
        }, 
        {
            "Dep": "3535", 
            "RaceEth": " Asian", 
            "Kids": "KidsOther", 
            "Emp2": "NILF", 
            "Educ": "LTHS"
        }, 
        {
            "Dep": "13817", 
            "RaceEth": " Asian", 
            "Kids": "None", 
            "Emp2": "EmpFull", 
            "Educ": "HsGrad"
        }, 
        {
            "Dep": "3629", 
            "RaceEth": " Asian", 
            "Kids": "None", 
            "Emp2": "EmpPart", 
            "Educ": "HsGrad"
        }, 
        {
            "Dep": "1576", 
            "RaceEth": " Asian", 
            "Kids": "None", 
            "Emp2": "Unempd", 
            "Educ": "HsGrad"
        }, 
        {
            "Dep": "8941", 
            "RaceEth": " Asian", 
            "Kids": "None", 
            "Emp2": "NILF", 
            "Educ": "HsGrad"
        }, 
        {
            "Dep": "19372", 
            "RaceEth": " Asian", 
            "Kids": "Kids<6", 
            "Emp2": "EmpFull", 
            "Educ": "HsGrad"
        }, 
        {
            "Dep": "6404", 
            "RaceEth": " Asian", 
            "Kids": "Kids<6", 
            "Emp2": "EmpPart", 
            "Educ": "HsGrad"
        }, 
        {
            "Dep": "1734", 
            "RaceEth": " Asian", 
            "Kids": "Kids<6", 
            "Emp2": "Unempd", 
            "Educ": "HsGrad"
        }, 
        {
            "Dep": "24697", 
            "RaceEth": " Asian", 
            "Kids": "Kids<6", 
            "Emp2": "NILF", 
            "Educ": "HsGrad"
        }, 
        {
            "Dep": "8106", 
            "RaceEth": " Asian", 
            "Kids": "KidsOther", 
            "Emp2": "EmpFull", 
            "Educ": "HsGrad"
        }, 
        {
            "Dep": "2185", 
            "RaceEth": " Asian", 
            "Kids": "KidsOther", 
            "Emp2": "EmpPart", 
            "Educ": "HsGrad"
        }, 
        {
            "Dep": "573", 
            "RaceEth": " Asian", 
            "Kids": "KidsOther", 
            "Emp2": "Unempd", 
            "Educ": "HsGrad"
        }, 
        {
            "Dep": "5217", 
            "RaceEth": " Asian", 
            "Kids": "KidsOther", 
            "Emp2": "NILF", 
            "Educ": "HsGrad"
        }, 
        {
            "Dep": "23135", 
            "RaceEth": " Asian", 
            "Kids": "None", 
            "Emp2": "EmpFull", 
            "Educ": "SomeColl"
        }, 
        {
            "Dep": "6049", 
            "RaceEth": " Asian", 
            "Kids": "None", 
            "Emp2": "EmpPart", 
            "Educ": "SomeColl"
        }, 
        {
            "Dep": "1949", 
            "RaceEth": " Asian", 
            "Kids": "None", 
            "Emp2": "Unempd", 
            "Educ": "SomeColl"
        }, 
        {
            "Dep": "12839", 
            "RaceEth": " Asian", 
            "Kids": "None", 
            "Emp2": "NILF", 
            "Educ": "SomeColl"
        }, 
        {
            "Dep": "33691", 
            "RaceEth": " Asian", 
            "Kids": "Kids<6", 
            "Emp2": "EmpFull", 
            "Educ": "SomeColl"
        }, 
        {
            "Dep": "8902", 
            "RaceEth": " Asian", 
            "Kids": "Kids<6", 
            "Emp2": "EmpPart", 
            "Educ": "SomeColl"
        }, 
        {
            "Dep": "2473", 
            "RaceEth": " Asian", 
            "Kids": "Kids<6", 
            "Emp2": "Unempd", 
            "Educ": "SomeColl"
        }, 
        {
            "Dep": "31309", 
            "RaceEth": " Asian", 
            "Kids": "Kids<6", 
            "Emp2": "NILF", 
            "Educ": "SomeColl"
        }, 
        {
            "Dep": "8955", 
            "RaceEth": " Asian", 
            "Kids": "KidsOther", 
            "Emp2": "EmpFull", 
            "Educ": "SomeColl"
        }, 
        {
            "Dep": "2291", 
            "RaceEth": " Asian", 
            "Kids": "KidsOther", 
            "Emp2": "EmpPart", 
            "Educ": "SomeColl"
        }, 
        {
            "Dep": "782", 
            "RaceEth": " Asian", 
            "Kids": "KidsOther", 
            "Emp2": "Unempd", 
            "Educ": "SomeColl"
        }, 
        {
            "Dep": "3982", 
            "RaceEth": " Asian", 
            "Kids": "KidsOther", 
            "Emp2": "NILF", 
            "Educ": "SomeColl"
        }, 
        {
            "Dep": "119894", 
            "RaceEth": " Asian", 
            "Kids": "None", 
            "Emp2": "EmpFull", 
            "Educ": "CollGrad"
        }, 
        {
            "Dep": "17288", 
            "RaceEth": " Asian", 
            "Kids": "None", 
            "Emp2": "EmpPart", 
            "Educ": "CollGrad"
        }, 
        {
            "Dep": "6410", 
            "RaceEth": " Asian", 
            "Kids": "None", 
            "Emp2": "Unempd", 
            "Educ": "CollGrad"
        }, 
        {
            "Dep": "55689", 
            "RaceEth": " Asian", 
            "Kids": "None", 
            "Emp2": "NILF", 
            "Educ": "CollGrad"
        }, 
        {
            "Dep": "100786", 
            "RaceEth": " Asian", 
            "Kids": "Kids<6", 
            "Emp2": "EmpFull", 
            "Educ": "CollGrad"
        }, 
        {
            "Dep": "22845", 
            "RaceEth": " Asian", 
            "Kids": "Kids<6", 
            "Emp2": "EmpPart", 
            "Educ": "CollGrad"
        }, 
        {
            "Dep": "6773", 
            "RaceEth": " Asian", 
            "Kids": "Kids<6", 
            "Emp2": "Unempd", 
            "Educ": "CollGrad"
        }, 
        {
            "Dep": "101021", 
            "RaceEth": " Asian", 
            "Kids": "Kids<6", 
            "Emp2": "NILF", 
            "Educ": "CollGrad"
        }, 
        {
            "Dep": "10836", 
            "RaceEth": " Asian", 
            "Kids": "KidsOther", 
            "Emp2": "EmpFull", 
            "Educ": "CollGrad"
        }, 
        {
            "Dep": "2342", 
            "RaceEth": " Asian", 
            "Kids": "KidsOther", 
            "Emp2": "EmpPart", 
            "Educ": "CollGrad"
        }, 
        {
            "Dep": "462", 
            "RaceEth": " Asian", 
            "Kids": "KidsOther", 
            "Emp2": "Unempd", 
            "Educ": "CollGrad"
        }, 
        {
            "Dep": "7779", 
            "RaceEth": " Asian", 
            "Kids": "KidsOther", 
            "Emp2": "NILF", 
            "Educ": "CollGrad"
        }, 
        {
            "Dep": "41460", 
            "RaceEth": " Hispanic", 
            "Kids": "None", 
            "Emp2": "EmpFull", 
            "Educ": "LTHS"
        }, 
        {
            "Dep": "11556", 
            "RaceEth": " Hispanic", 
            "Kids": "None", 
            "Emp2": "EmpPart", 
            "Educ": "LTHS"
        }, 
        {
            "Dep": "8002", 
            "RaceEth": " Hispanic", 
            "Kids": "None", 
            "Emp2": "Unempd", 
            "Educ": "LTHS"
        }, 
        {
            "Dep": "50834", 
            "RaceEth": " Hispanic", 
            "Kids": "None", 
            "Emp2": "NILF", 
            "Educ": "LTHS"
        }, 
        {
            "Dep": "83911", 
            "RaceEth": " Hispanic", 
            "Kids": "Kids<6", 
            "Emp2": "EmpFull", 
            "Educ": "LTHS"
        }, 
        {
            "Dep": "35914", 
            "RaceEth": " Hispanic", 
            "Kids": "Kids<6", 
            "Emp2": "EmpPart", 
            "Educ": "LTHS"
        }, 
        {
            "Dep": "19627", 
            "RaceEth": " Hispanic", 
            "Kids": "Kids<6", 
            "Emp2": "Unempd", 
            "Educ": "LTHS"
        }, 
        {
            "Dep": "249000", 
            "RaceEth": " Hispanic", 
            "Kids": "Kids<6", 
            "Emp2": "NILF", 
            "Educ": "LTHS"
        }, 
        {
            "Dep": "45508", 
            "RaceEth": " Hispanic", 
            "Kids": "KidsOther", 
            "Emp2": "EmpFull", 
            "Educ": "LTHS"
        }, 
        {
            "Dep": "16895", 
            "RaceEth": " Hispanic", 
            "Kids": "KidsOther", 
            "Emp2": "EmpPart", 
            "Educ": "LTHS"
        }, 
        {
            "Dep": "8058", 
            "RaceEth": " Hispanic", 
            "Kids": "KidsOther", 
            "Emp2": "Unempd", 
            "Educ": "LTHS"
        }, 
        {
            "Dep": "57669", 
            "RaceEth": " Hispanic", 
            "Kids": "KidsOther", 
            "Emp2": "NILF", 
            "Educ": "LTHS"
        }, 
        {
            "Dep": "51841", 
            "RaceEth": " Hispanic", 
            "Kids": "None", 
            "Emp2": "EmpFull", 
            "Educ": "HsGrad"
        }, 
        {
            "Dep": "11079", 
            "RaceEth": " Hispanic", 
            "Kids": "None", 
            "Emp2": "EmpPart", 
            "Educ": "HsGrad"
        }, 
        {
            "Dep": "6112", 
            "RaceEth": " Hispanic", 
            "Kids": "None", 
            "Emp2": "Unempd", 
            "Educ": "HsGrad"
        }, 
        {
            "Dep": "34721", 
            "RaceEth": " Hispanic", 
            "Kids": "None", 
            "Emp2": "NILF", 
            "Educ": "HsGrad"
        }, 
        {
            "Dep": "110420", 
            "RaceEth": " Hispanic", 
            "Kids": "Kids<6", 
            "Emp2": "EmpFull", 
            "Educ": "HsGrad"
        }, 
        {
            "Dep": "35121", 
            "RaceEth": " Hispanic", 
            "Kids": "Kids<6", 
            "Emp2": "EmpPart", 
            "Educ": "HsGrad"
        }, 
        {
            "Dep": "14338", 
            "RaceEth": " Hispanic", 
            "Kids": "Kids<6", 
            "Emp2": "Unempd", 
            "Educ": "HsGrad"
        }, 
        {
            "Dep": "157335", 
            "RaceEth": " Hispanic", 
            "Kids": "Kids<6", 
            "Emp2": "NILF", 
            "Educ": "HsGrad"
        }, 
        {
            "Dep": "53204", 
            "RaceEth": " Hispanic", 
            "Kids": "KidsOther", 
            "Emp2": "EmpFull", 
            "Educ": "HsGrad"
        }, 
        {
            "Dep": "14427", 
            "RaceEth": " Hispanic", 
            "Kids": "KidsOther", 
            "Emp2": "EmpPart", 
            "Educ": "HsGrad"
        }, 
        {
            "Dep": "5251", 
            "RaceEth": " Hispanic", 
            "Kids": "KidsOther", 
            "Emp2": "Unempd", 
            "Educ": "HsGrad"
        }, 
        {
            "Dep": "36025", 
            "RaceEth": " Hispanic", 
            "Kids": "KidsOther", 
            "Emp2": "NILF", 
            "Educ": "HsGrad"
        }, 
        {
            "Dep": "57609", 
            "RaceEth": " Hispanic", 
            "Kids": "None", 
            "Emp2": "EmpFull", 
            "Educ": "SomeColl"
        }, 
        {
            "Dep": "12498", 
            "RaceEth": " Hispanic", 
            "Kids": "None", 
            "Emp2": "EmpPart", 
            "Educ": "SomeColl"
        }, 
        {
            "Dep": "3691", 
            "RaceEth": " Hispanic", 
            "Kids": "None", 
            "Emp2": "Unempd", 
            "Educ": "SomeColl"
        }, 
        {
            "Dep": "17832", 
            "RaceEth": " Hispanic", 
            "Kids": "None", 
            "Emp2": "NILF", 
            "Educ": "SomeColl"
        }, 
        {
            "Dep": "122919", 
            "RaceEth": " Hispanic", 
            "Kids": "Kids<6", 
            "Emp2": "EmpFull", 
            "Educ": "SomeColl"
        }, 
        {
            "Dep": "38207", 
            "RaceEth": " Hispanic", 
            "Kids": "Kids<6", 
            "Emp2": "EmpPart", 
            "Educ": "SomeColl"
        }, 
        {
            "Dep": "10733", 
            "RaceEth": " Hispanic", 
            "Kids": "Kids<6", 
            "Emp2": "Unempd", 
            "Educ": "SomeColl"
        }, 
        {
            "Dep": "95630", 
            "RaceEth": " Hispanic", 
            "Kids": "Kids<6", 
            "Emp2": "NILF", 
            "Educ": "SomeColl"
        }, 
        {
            "Dep": "48605", 
            "RaceEth": " Hispanic", 
            "Kids": "KidsOther", 
            "Emp2": "EmpFull", 
            "Educ": "SomeColl"
        }, 
        {
            "Dep": "12288", 
            "RaceEth": " Hispanic", 
            "Kids": "KidsOther", 
            "Emp2": "EmpPart", 
            "Educ": "SomeColl"
        }, 
        {
            "Dep": "3693", 
            "RaceEth": " Hispanic", 
            "Kids": "KidsOther", 
            "Emp2": "Unempd", 
            "Educ": "SomeColl"
        }, 
        {
            "Dep": "16457", 
            "RaceEth": " Hispanic", 
            "Kids": "KidsOther", 
            "Emp2": "NILF", 
            "Educ": "SomeColl"
        }, 
        {
            "Dep": "78409", 
            "RaceEth": " Hispanic", 
            "Kids": "None", 
            "Emp2": "EmpFull", 
            "Educ": "CollGrad"
        }, 
        {
            "Dep": "9801", 
            "RaceEth": " Hispanic", 
            "Kids": "None", 
            "Emp2": "EmpPart", 
            "Educ": "CollGrad"
        }, 
        {
            "Dep": "2877", 
            "RaceEth": " Hispanic", 
            "Kids": "None", 
            "Emp2": "Unempd", 
            "Educ": "CollGrad"
        }, 
        {
            "Dep": "14050", 
            "RaceEth": " Hispanic", 
            "Kids": "None", 
            "Emp2": "NILF", 
            "Educ": "CollGrad"
        }, 
        {
            "Dep": "74828", 
            "RaceEth": " Hispanic", 
            "Kids": "Kids<6", 
            "Emp2": "EmpFull", 
            "Educ": "CollGrad"
        }, 
        {
            "Dep": "18215", 
            "RaceEth": " Hispanic", 
            "Kids": "Kids<6", 
            "Emp2": "EmpPart", 
            "Educ": "CollGrad"
        }, 
        {
            "Dep": "3509", 
            "RaceEth": " Hispanic", 
            "Kids": "Kids<6", 
            "Emp2": "Unempd", 
            "Educ": "CollGrad"
        }, 
        {
            "Dep": "42326", 
            "RaceEth": " Hispanic", 
            "Kids": "Kids<6", 
            "Emp2": "NILF", 
            "Educ": "CollGrad"
        }, 
        {
            "Dep": "14995", 
            "RaceEth": " Hispanic", 
            "Kids": "KidsOther", 
            "Emp2": "EmpFull", 
            "Educ": "CollGrad"
        }, 
        {
            "Dep": "2549", 
            "RaceEth": " Hispanic", 
            "Kids": "KidsOther", 
            "Emp2": "EmpPart", 
            "Educ": "CollGrad"
        }, 
        {
            "Dep": "1026", 
            "RaceEth": " Hispanic", 
            "Kids": "KidsOther", 
            "Emp2": "Unempd", 
            "Educ": "CollGrad"
        }, 
        {
            "Dep": "5068", 
            "RaceEth": " Hispanic", 
            "Kids": "KidsOther", 
            "Emp2": "NILF", 
            "Educ": "CollGrad"
        }, 
        {
            "Dep": "706", 
            "RaceEth": " AmIndian", 
            "Kids": "None", 
            "Emp2": "EmpFull", 
            "Educ": "LTHS"
        }, 
        {
            "Dep": "299", 
            "RaceEth": " AmIndian", 
            "Kids": "None", 
            "Emp2": "EmpPart", 
            "Educ": "LTHS"
        }, 
        {
            "Dep": "216", 
            "RaceEth": " AmIndian", 
            "Kids": "None", 
            "Emp2": "Unempd", 
            "Educ": "LTHS"
        }, 
        {
            "Dep": "946", 
            "RaceEth": " AmIndian", 
            "Kids": "None", 
            "Emp2": "NILF", 
            "Educ": "LTHS"
        }, 
        {
            "Dep": "1284", 
            "RaceEth": " AmIndian", 
            "Kids": "Kids<6", 
            "Emp2": "EmpFull", 
            "Educ": "LTHS"
        }, 
        {
            "Dep": "452", 
            "RaceEth": " AmIndian", 
            "Kids": "Kids<6", 
            "Emp2": "EmpPart", 
            "Educ": "LTHS"
        }, 
        {
            "Dep": "298", 
            "RaceEth": " AmIndian", 
            "Kids": "Kids<6", 
            "Emp2": "Unempd", 
            "Educ": "LTHS"
        }, 
        {
            "Dep": "4044", 
            "RaceEth": " AmIndian", 
            "Kids": "Kids<6", 
            "Emp2": "NILF", 
            "Educ": "LTHS"
        }, 
        {
            "Dep": "643", 
            "RaceEth": " AmIndian", 
            "Kids": "KidsOther", 
            "Emp2": "EmpFull", 
            "Educ": "LTHS"
        }, 
        {
            "Dep": "567", 
            "RaceEth": " AmIndian", 
            "Kids": "KidsOther", 
            "Emp2": "EmpPart", 
            "Educ": "LTHS"
        }, 
        {
            "Dep": "156", 
            "RaceEth": " AmIndian", 
            "Kids": "KidsOther", 
            "Emp2": "Unempd", 
            "Educ": "LTHS"
        }, 
        {
            "Dep": "1566", 
            "RaceEth": " AmIndian", 
            "Kids": "KidsOther", 
            "Emp2": "NILF", 
            "Educ": "LTHS"
        }, 
        {
            "Dep": "1462", 
            "RaceEth": " AmIndian", 
            "Kids": "None", 
            "Emp2": "EmpFull", 
            "Educ": "HsGrad"
        }, 
        {
            "Dep": "504", 
            "RaceEth": " AmIndian", 
            "Kids": "None", 
            "Emp2": "EmpPart", 
            "Educ": "HsGrad"
        }, 
        {
            "Dep": "376", 
            "RaceEth": " AmIndian", 
            "Kids": "None", 
            "Emp2": "Unempd", 
            "Educ": "HsGrad"
        }, 
        {
            "Dep": "1047", 
            "RaceEth": " AmIndian", 
            "Kids": "None", 
            "Emp2": "NILF", 
            "Educ": "HsGrad"
        }, 
        {
            "Dep": "3447", 
            "RaceEth": " AmIndian", 
            "Kids": "Kids<6", 
            "Emp2": "EmpFull", 
            "Educ": "HsGrad"
        }, 
        {
            "Dep": "1400", 
            "RaceEth": " AmIndian", 
            "Kids": "Kids<6", 
            "Emp2": "EmpPart", 
            "Educ": "HsGrad"
        }, 
        {
            "Dep": "613", 
            "RaceEth": " AmIndian", 
            "Kids": "Kids<6", 
            "Emp2": "Unempd", 
            "Educ": "HsGrad"
        }, 
        {
            "Dep": "4724", 
            "RaceEth": " AmIndian", 
            "Kids": "Kids<6", 
            "Emp2": "NILF", 
            "Educ": "HsGrad"
        }, 
        {
            "Dep": "2414", 
            "RaceEth": " AmIndian", 
            "Kids": "KidsOther", 
            "Emp2": "EmpFull", 
            "Educ": "HsGrad"
        }, 
        {
            "Dep": "767", 
            "RaceEth": " AmIndian", 
            "Kids": "KidsOther", 
            "Emp2": "EmpPart", 
            "Educ": "HsGrad"
        }, 
        {
            "Dep": "276", 
            "RaceEth": " AmIndian", 
            "Kids": "KidsOther", 
            "Emp2": "Unempd", 
            "Educ": "HsGrad"
        }, 
        {
            "Dep": "1925", 
            "RaceEth": " AmIndian", 
            "Kids": "KidsOther", 
            "Emp2": "NILF", 
            "Educ": "HsGrad"
        }, 
        {
            "Dep": "3161", 
            "RaceEth": " AmIndian", 
            "Kids": "None", 
            "Emp2": "EmpFull", 
            "Educ": "SomeColl"
        }, 
        {
            "Dep": "619", 
            "RaceEth": " AmIndian", 
            "Kids": "None", 
            "Emp2": "EmpPart", 
            "Educ": "SomeColl"
        }, 
        {
            "Dep": "177", 
            "RaceEth": " AmIndian", 
            "Kids": "None", 
            "Emp2": "Unempd", 
            "Educ": "SomeColl"
        }, 
        {
            "Dep": "1225", 
            "RaceEth": " AmIndian", 
            "Kids": "None", 
            "Emp2": "NILF", 
            "Educ": "SomeColl"
        }, 
        {
            "Dep": "7303", 
            "RaceEth": " AmIndian", 
            "Kids": "Kids<6", 
            "Emp2": "EmpFull", 
            "Educ": "SomeColl"
        }, 
        {
            "Dep": "1543", 
            "RaceEth": " AmIndian", 
            "Kids": "Kids<6", 
            "Emp2": "EmpPart", 
            "Educ": "SomeColl"
        }, 
        {
            "Dep": "324", 
            "RaceEth": " AmIndian", 
            "Kids": "Kids<6", 
            "Emp2": "Unempd", 
            "Educ": "SomeColl"
        }, 
        {
            "Dep": "5189", 
            "RaceEth": " AmIndian", 
            "Kids": "Kids<6", 
            "Emp2": "NILF", 
            "Educ": "SomeColl"
        }, 
        {
            "Dep": "3096", 
            "RaceEth": " AmIndian", 
            "Kids": "KidsOther", 
            "Emp2": "EmpFull", 
            "Educ": "SomeColl"
        }, 
        {
            "Dep": "794", 
            "RaceEth": " AmIndian", 
            "Kids": "KidsOther", 
            "Emp2": "EmpPart", 
            "Educ": "SomeColl"
        }, 
        {
            "Dep": "127", 
            "RaceEth": " AmIndian", 
            "Kids": "KidsOther", 
            "Emp2": "Unempd", 
            "Educ": "SomeColl"
        }, 
        {
            "Dep": "1148", 
            "RaceEth": " AmIndian", 
            "Kids": "KidsOther", 
            "Emp2": "NILF", 
            "Educ": "SomeColl"
        }, 
        {
            "Dep": "2689", 
            "RaceEth": " AmIndian", 
            "Kids": "None", 
            "Emp2": "EmpFull", 
            "Educ": "CollGrad"
        }, 
        {
            "Dep": "170", 
            "RaceEth": " AmIndian", 
            "Kids": "None", 
            "Emp2": "EmpPart", 
            "Educ": "CollGrad"
        }, 
        {
            "Dep": "150", 
            "RaceEth": " AmIndian", 
            "Kids": "None", 
            "Emp2": "Unempd", 
            "Educ": "CollGrad"
        }, 
        {
            "Dep": "263", 
            "RaceEth": " AmIndian", 
            "Kids": "None", 
            "Emp2": "NILF", 
            "Educ": "CollGrad"
        }, 
        {
            "Dep": "4112", 
            "RaceEth": " AmIndian", 
            "Kids": "Kids<6", 
            "Emp2": "EmpFull", 
            "Educ": "CollGrad"
        }, 
        {
            "Dep": "1120", 
            "RaceEth": " AmIndian", 
            "Kids": "Kids<6", 
            "Emp2": "EmpPart", 
            "Educ": "CollGrad"
        }, 
        {
            "Dep": "100", 
            "RaceEth": " AmIndian", 
            "Kids": "Kids<6", 
            "Emp2": "Unempd", 
            "Educ": "CollGrad"
        }, 
        {
            "Dep": "1647", 
            "RaceEth": " AmIndian", 
            "Kids": "Kids<6", 
            "Emp2": "NILF", 
            "Educ": "CollGrad"
        }, 
        {
            "Dep": "1068", 
            "RaceEth": " AmIndian", 
            "Kids": "KidsOther", 
            "Emp2": "EmpFull", 
            "Educ": "CollGrad"
        }, 
        {
            "Dep": "257", 
            "RaceEth": " AmIndian", 
            "Kids": "KidsOther", 
            "Emp2": "EmpPart", 
            "Educ": "CollGrad"
        }, 
        {
            "Dep": "59", 
            "RaceEth": " AmIndian", 
            "Kids": "KidsOther", 
            "Emp2": "Unempd", 
            "Educ": "CollGrad"
        }, 
        {
            "Dep": "292", 
            "RaceEth": " AmIndian", 
            "Kids": "KidsOther", 
            "Emp2": "NILF", 
            "Educ": "CollGrad"
        }, 
        {
            "Dep": "404", 
            "RaceEth": " NHOther", 
            "Kids": "None", 
            "Emp2": "EmpFull", 
            "Educ": "LTHS"
        }, 
        {
            "Dep": "52", 
            "RaceEth": " NHOther", 
            "Kids": "None", 
            "Emp2": "EmpPart", 
            "Educ": "LTHS"
        }, 
        {
            "Dep": "0", 
            "RaceEth": " NHOther", 
            "Kids": "None", 
            "Emp2": "Unempd", 
            "Educ": "LTHS"
        }, 
        {
            "Dep": "708", 
            "RaceEth": " NHOther", 
            "Kids": "None", 
            "Emp2": "NILF", 
            "Educ": "LTHS"
        }, 
        {
            "Dep": "465", 
            "RaceEth": " NHOther", 
            "Kids": "Kids<6", 
            "Emp2": "EmpFull", 
            "Educ": "LTHS"
        }, 
        {
            "Dep": "353", 
            "RaceEth": " NHOther", 
            "Kids": "Kids<6", 
            "Emp2": "EmpPart", 
            "Educ": "LTHS"
        }, 
        {
            "Dep": "32", 
            "RaceEth": " NHOther", 
            "Kids": "Kids<6", 
            "Emp2": "Unempd", 
            "Educ": "LTHS"
        }, 
        {
            "Dep": "1367", 
            "RaceEth": " NHOther", 
            "Kids": "Kids<6", 
            "Emp2": "NILF", 
            "Educ": "LTHS"
        }, 
        {
            "Dep": "502", 
            "RaceEth": " NHOther", 
            "Kids": "KidsOther", 
            "Emp2": "EmpFull", 
            "Educ": "LTHS"
        }, 
        {
            "Dep": "400", 
            "RaceEth": " NHOther", 
            "Kids": "KidsOther", 
            "Emp2": "EmpPart", 
            "Educ": "LTHS"
        }, 
        {
            "Dep": "24", 
            "RaceEth": " NHOther", 
            "Kids": "KidsOther", 
            "Emp2": "Unempd", 
            "Educ": "LTHS"
        }, 
        {
            "Dep": "179", 
            "RaceEth": " NHOther", 
            "Kids": "KidsOther", 
            "Emp2": "NILF", 
            "Educ": "LTHS"
        }, 
        {
            "Dep": "2118", 
            "RaceEth": " NHOther", 
            "Kids": "None", 
            "Emp2": "EmpFull", 
            "Educ": "HsGrad"
        }, 
        {
            "Dep": "284", 
            "RaceEth": " NHOther", 
            "Kids": "None", 
            "Emp2": "EmpPart", 
            "Educ": "HsGrad"
        }, 
        {
            "Dep": "103", 
            "RaceEth": " NHOther", 
            "Kids": "None", 
            "Emp2": "Unempd", 
            "Educ": "HsGrad"
        }, 
        {
            "Dep": "841", 
            "RaceEth": " NHOther", 
            "Kids": "None", 
            "Emp2": "NILF", 
            "Educ": "HsGrad"
        }, 
        {
            "Dep": "1282", 
            "RaceEth": " NHOther", 
            "Kids": "Kids<6", 
            "Emp2": "EmpFull", 
            "Educ": "HsGrad"
        }, 
        {
            "Dep": "248", 
            "RaceEth": " NHOther", 
            "Kids": "Kids<6", 
            "Emp2": "EmpPart", 
            "Educ": "HsGrad"
        }, 
        {
            "Dep": "239", 
            "RaceEth": " NHOther", 
            "Kids": "Kids<6", 
            "Emp2": "Unempd", 
            "Educ": "HsGrad"
        }, 
        {
            "Dep": "2436", 
            "RaceEth": " NHOther", 
            "Kids": "Kids<6", 
            "Emp2": "NILF", 
            "Educ": "HsGrad"
        }, 
        {
            "Dep": "832", 
            "RaceEth": " NHOther", 
            "Kids": "KidsOther", 
            "Emp2": "EmpFull", 
            "Educ": "HsGrad"
        }, 
        {
            "Dep": "372", 
            "RaceEth": " NHOther", 
            "Kids": "KidsOther", 
            "Emp2": "EmpPart", 
            "Educ": "HsGrad"
        }, 
        {
            "Dep": "89", 
            "RaceEth": " NHOther", 
            "Kids": "KidsOther", 
            "Emp2": "Unempd", 
            "Educ": "HsGrad"
        }, 
        {
            "Dep": "264", 
            "RaceEth": " NHOther", 
            "Kids": "KidsOther", 
            "Emp2": "NILF", 
            "Educ": "HsGrad"
        }, 
        {
            "Dep": "1254", 
            "RaceEth": " NHOther", 
            "Kids": "None", 
            "Emp2": "EmpFull", 
            "Educ": "SomeColl"
        }, 
        {
            "Dep": "258", 
            "RaceEth": " NHOther", 
            "Kids": "None", 
            "Emp2": "EmpPart", 
            "Educ": "SomeColl"
        }, 
        {
            "Dep": "43", 
            "RaceEth": " NHOther", 
            "Kids": "None", 
            "Emp2": "Unempd", 
            "Educ": "SomeColl"
        }, 
        {
            "Dep": "442", 
            "RaceEth": " NHOther", 
            "Kids": "None", 
            "Emp2": "NILF", 
            "Educ": "SomeColl"
        }, 
        {
            "Dep": "1899", 
            "RaceEth": " NHOther", 
            "Kids": "Kids<6", 
            "Emp2": "EmpFull", 
            "Educ": "SomeColl"
        }, 
        {
            "Dep": "625", 
            "RaceEth": " NHOther", 
            "Kids": "Kids<6", 
            "Emp2": "EmpPart", 
            "Educ": "SomeColl"
        }, 
        {
            "Dep": "219", 
            "RaceEth": " NHOther", 
            "Kids": "Kids<6", 
            "Emp2": "Unempd", 
            "Educ": "SomeColl"
        }, 
        {
            "Dep": "1746", 
            "RaceEth": " NHOther", 
            "Kids": "Kids<6", 
            "Emp2": "NILF", 
            "Educ": "SomeColl"
        }, 
        {
            "Dep": "468", 
            "RaceEth": " NHOther", 
            "Kids": "KidsOther", 
            "Emp2": "EmpFull", 
            "Educ": "SomeColl"
        }, 
        {
            "Dep": "226", 
            "RaceEth": " NHOther", 
            "Kids": "KidsOther", 
            "Emp2": "EmpPart", 
            "Educ": "SomeColl"
        }, 
        {
            "Dep": "71", 
            "RaceEth": " NHOther", 
            "Kids": "KidsOther", 
            "Emp2": "Unempd", 
            "Educ": "SomeColl"
        }, 
        {
            "Dep": "370", 
            "RaceEth": " NHOther", 
            "Kids": "KidsOther", 
            "Emp2": "NILF", 
            "Educ": "SomeColl"
        }, 
        {
            "Dep": "3004", 
            "RaceEth": " NHOther", 
            "Kids": "None", 
            "Emp2": "EmpFull", 
            "Educ": "CollGrad"
        }, 
        {
            "Dep": "398", 
            "RaceEth": " NHOther", 
            "Kids": "None", 
            "Emp2": "EmpPart", 
            "Educ": "CollGrad"
        }, 
        {
            "Dep": "201", 
            "RaceEth": " NHOther", 
            "Kids": "None", 
            "Emp2": "Unempd", 
            "Educ": "CollGrad"
        }, 
        {
            "Dep": "1493", 
            "RaceEth": " NHOther", 
            "Kids": "None", 
            "Emp2": "NILF", 
            "Educ": "CollGrad"
        }, 
        {
            "Dep": "2289", 
            "RaceEth": " NHOther", 
            "Kids": "Kids<6", 
            "Emp2": "EmpFull", 
            "Educ": "CollGrad"
        }, 
        {
            "Dep": "503", 
            "RaceEth": " NHOther", 
            "Kids": "Kids<6", 
            "Emp2": "EmpPart", 
            "Educ": "CollGrad"
        }, 
        {
            "Dep": "130", 
            "RaceEth": " NHOther", 
            "Kids": "Kids<6", 
            "Emp2": "Unempd", 
            "Educ": "CollGrad"
        }, 
        {
            "Dep": "2584", 
            "RaceEth": " NHOther", 
            "Kids": "Kids<6", 
            "Emp2": "NILF", 
            "Educ": "CollGrad"
        }, 
        {
            "Dep": "421", 
            "RaceEth": " NHOther", 
            "Kids": "KidsOther", 
            "Emp2": "EmpFull", 
            "Educ": "CollGrad"
        }, 
        {
            "Dep": "189", 
            "RaceEth": " NHOther", 
            "Kids": "KidsOther", 
            "Emp2": "EmpPart", 
            "Educ": "CollGrad"
        }, 
        {
            "Dep": "0", 
            "RaceEth": " NHOther", 
            "Kids": "KidsOther", 
            "Emp2": "Unempd", 
            "Educ": "CollGrad"
        }, 
        {
            "Dep": "66", 
            "RaceEth": " NHOther", 
            "Kids": "KidsOther", 
            "Emp2": "NILF", 
            "Educ": "CollGrad"
        }, 
        {
            "Dep": "142", 
            "RaceEth": " NHMulti", 
            "Kids": "None", 
            "Emp2": "EmpFull", 
            "Educ": "LTHS"
        }, 
        {
            "Dep": "405", 
            "RaceEth": " NHMulti", 
            "Kids": "None", 
            "Emp2": "EmpPart", 
            "Educ": "LTHS"
        }, 
        {
            "Dep": "0", 
            "RaceEth": " NHMulti", 
            "Kids": "None", 
            "Emp2": "Unempd", 
            "Educ": "LTHS"
        }, 
        {
            "Dep": "539", 
            "RaceEth": " NHMulti", 
            "Kids": "None", 
            "Emp2": "NILF", 
            "Educ": "LTHS"
        }, 
        {
            "Dep": "1047", 
            "RaceEth": " NHMulti", 
            "Kids": "Kids<6", 
            "Emp2": "EmpFull", 
            "Educ": "LTHS"
        }, 
        {
            "Dep": "500", 
            "RaceEth": " NHMulti", 
            "Kids": "Kids<6", 
            "Emp2": "EmpPart", 
            "Educ": "LTHS"
        }, 
        {
            "Dep": "242", 
            "RaceEth": " NHMulti", 
            "Kids": "Kids<6", 
            "Emp2": "Unempd", 
            "Educ": "LTHS"
        }, 
        {
            "Dep": "1806", 
            "RaceEth": " NHMulti", 
            "Kids": "Kids<6", 
            "Emp2": "NILF", 
            "Educ": "LTHS"
        }, 
        {
            "Dep": "811", 
            "RaceEth": " NHMulti", 
            "Kids": "KidsOther", 
            "Emp2": "EmpFull", 
            "Educ": "LTHS"
        }, 
        {
            "Dep": "358", 
            "RaceEth": " NHMulti", 
            "Kids": "KidsOther", 
            "Emp2": "EmpPart", 
            "Educ": "LTHS"
        }, 
        {
            "Dep": "159", 
            "RaceEth": " NHMulti", 
            "Kids": "KidsOther", 
            "Emp2": "Unempd", 
            "Educ": "LTHS"
        }, 
        {
            "Dep": "662", 
            "RaceEth": " NHMulti", 
            "Kids": "KidsOther", 
            "Emp2": "NILF", 
            "Educ": "LTHS"
        }, 
        {
            "Dep": "2146", 
            "RaceEth": " NHMulti", 
            "Kids": "None", 
            "Emp2": "EmpFull", 
            "Educ": "HsGrad"
        }, 
        {
            "Dep": "794", 
            "RaceEth": " NHMulti", 
            "Kids": "None", 
            "Emp2": "EmpPart", 
            "Educ": "HsGrad"
        }, 
        {
            "Dep": "415", 
            "RaceEth": " NHMulti", 
            "Kids": "None", 
            "Emp2": "Unempd", 
            "Educ": "HsGrad"
        }, 
        {
            "Dep": "1323", 
            "RaceEth": " NHMulti", 
            "Kids": "None", 
            "Emp2": "NILF", 
            "Educ": "HsGrad"
        }, 
        {
            "Dep": "4472", 
            "RaceEth": " NHMulti", 
            "Kids": "Kids<6", 
            "Emp2": "EmpFull", 
            "Educ": "HsGrad"
        }, 
        {
            "Dep": "2912", 
            "RaceEth": " NHMulti", 
            "Kids": "Kids<6", 
            "Emp2": "EmpPart", 
            "Educ": "HsGrad"
        }, 
        {
            "Dep": "933", 
            "RaceEth": " NHMulti", 
            "Kids": "Kids<6", 
            "Emp2": "Unempd", 
            "Educ": "HsGrad"
        }, 
        {
            "Dep": "5592", 
            "RaceEth": " NHMulti", 
            "Kids": "Kids<6", 
            "Emp2": "NILF", 
            "Educ": "HsGrad"
        }, 
        {
            "Dep": "3001", 
            "RaceEth": " NHMulti", 
            "Kids": "KidsOther", 
            "Emp2": "EmpFull", 
            "Educ": "HsGrad"
        }, 
        {
            "Dep": "602", 
            "RaceEth": " NHMulti", 
            "Kids": "KidsOther", 
            "Emp2": "EmpPart", 
            "Educ": "HsGrad"
        }, 
        {
            "Dep": "364", 
            "RaceEth": " NHMulti", 
            "Kids": "KidsOther", 
            "Emp2": "Unempd", 
            "Educ": "HsGrad"
        }, 
        {
            "Dep": "1207", 
            "RaceEth": " NHMulti", 
            "Kids": "KidsOther", 
            "Emp2": "NILF", 
            "Educ": "HsGrad"
        }, 
        {
            "Dep": "6560", 
            "RaceEth": " NHMulti", 
            "Kids": "None", 
            "Emp2": "EmpFull", 
            "Educ": "SomeColl"
        }, 
        {
            "Dep": "1343", 
            "RaceEth": " NHMulti", 
            "Kids": "None", 
            "Emp2": "EmpPart", 
            "Educ": "SomeColl"
        }, 
        {
            "Dep": "437", 
            "RaceEth": " NHMulti", 
            "Kids": "None", 
            "Emp2": "Unempd", 
            "Educ": "SomeColl"
        }, 
        {
            "Dep": "2275", 
            "RaceEth": " NHMulti", 
            "Kids": "None", 
            "Emp2": "NILF", 
            "Educ": "SomeColl"
        }, 
        {
            "Dep": "11147", 
            "RaceEth": " NHMulti", 
            "Kids": "Kids<6", 
            "Emp2": "EmpFull", 
            "Educ": "SomeColl"
        }, 
        {
            "Dep": "5652", 
            "RaceEth": " NHMulti", 
            "Kids": "Kids<6", 
            "Emp2": "EmpPart", 
            "Educ": "SomeColl"
        }, 
        {
            "Dep": "1272", 
            "RaceEth": " NHMulti", 
            "Kids": "Kids<6", 
            "Emp2": "Unempd", 
            "Educ": "SomeColl"
        }, 
        {
            "Dep": "9996", 
            "RaceEth": " NHMulti", 
            "Kids": "Kids<6", 
            "Emp2": "NILF", 
            "Educ": "SomeColl"
        }, 
        {
            "Dep": "5061", 
            "RaceEth": " NHMulti", 
            "Kids": "KidsOther", 
            "Emp2": "EmpFull", 
            "Educ": "SomeColl"
        }, 
        {
            "Dep": "1417", 
            "RaceEth": " NHMulti", 
            "Kids": "KidsOther", 
            "Emp2": "EmpPart", 
            "Educ": "SomeColl"
        }, 
        {
            "Dep": "586", 
            "RaceEth": " NHMulti", 
            "Kids": "KidsOther", 
            "Emp2": "Unempd", 
            "Educ": "SomeColl"
        }, 
        {
            "Dep": "2129", 
            "RaceEth": " NHMulti", 
            "Kids": "KidsOther", 
            "Emp2": "NILF", 
            "Educ": "SomeColl"
        }, 
        {
            "Dep": "11748", 
            "RaceEth": " NHMulti", 
            "Kids": "None", 
            "Emp2": "EmpFull", 
            "Educ": "CollGrad"
        }, 
        {
            "Dep": "1717", 
            "RaceEth": " NHMulti", 
            "Kids": "None", 
            "Emp2": "EmpPart", 
            "Educ": "CollGrad"
        }, 
        {
            "Dep": "664", 
            "RaceEth": " NHMulti", 
            "Kids": "None", 
            "Emp2": "Unempd", 
            "Educ": "CollGrad"
        }, 
        {
            "Dep": "2103", 
            "RaceEth": " NHMulti", 
            "Kids": "None", 
            "Emp2": "NILF", 
            "Educ": "CollGrad"
        }, 
        {
            "Dep": "10327", 
            "RaceEth": " NHMulti", 
            "Kids": "Kids<6", 
            "Emp2": "EmpFull", 
            "Educ": "CollGrad"
        }, 
        {
            "Dep": "2455", 
            "RaceEth": " NHMulti", 
            "Kids": "Kids<6", 
            "Emp2": "EmpPart", 
            "Educ": "CollGrad"
        }, 
        {
            "Dep": "314", 
            "RaceEth": " NHMulti", 
            "Kids": "Kids<6", 
            "Emp2": "Unempd", 
            "Educ": "CollGrad"
        }, 
        {
            "Dep": "5637", 
            "RaceEth": " NHMulti", 
            "Kids": "Kids<6", 
            "Emp2": "NILF", 
            "Educ": "CollGrad"
        }, 
        {
            "Dep": "1973", 
            "RaceEth": " NHMulti", 
            "Kids": "KidsOther", 
            "Emp2": "EmpFull", 
            "Educ": "CollGrad"
        }, 
        {
            "Dep": "472", 
            "RaceEth": " NHMulti", 
            "Kids": "KidsOther", 
            "Emp2": "EmpPart", 
            "Educ": "CollGrad"
        }, 
        {
            "Dep": "66", 
            "RaceEth": " NHMulti", 
            "Kids": "KidsOther", 
            "Emp2": "Unempd", 
            "Educ": "CollGrad"
        }, 
        {
            "Dep": "526", 
            "RaceEth": " NHMulti", 
            "Kids": "KidsOther", 
            "Emp2": "NILF", 
            "Educ": "CollGrad"
        }
    ]
}